AHCodeCompiler/__init__.py
AHCodeCompiler/compiler.py
AHCodeCompiler/config.py
AHCodeCompiler/editor.py
AHCodeCompiler/execute.py
AHCodeCompiler/runtimes.py
ahcodecompiler-1.0.5.dist-info/licenses/LICENSE
ahcodecompiler-1.0.5.dist-info/METADATA
ahcodecompiler-1.0.5.dist-info/WHEEL
ahcodecompiler-1.0.5.dist-info/top_level.txt
ahcodecompiler-1.0.5.dist-info/RECORD
