Metadata-Version: 2.4
Name: AHCodeCompiler
Version: 1.0.5
Summary: A powerful Python SDK and interactive CLI editor by Akash Halder for compiling and executing code with rich terminal output and supports for 50+ programming languages.
Home-page: https://akashhalder.in/
Author: Akash Halder
License: MIT
Classifier: Intended Audience :: Developers
Classifier: Topic :: Software Development :: Libraries
Classifier: Programming Language :: Python :: 3
Classifier: Operating System :: OS Independent
Requires-Python: >=3.10
License-File: LICENSE
Requires-Dist: requests
Requires-Dist: rich
Requires-Dist: pyfiglet
Dynamic: author
Dynamic: classifier
Dynamic: description
Dynamic: description-content-type
Dynamic: home-page
Dynamic: license
Dynamic: license-file
Dynamic: requires-dist
Dynamic: requires-python
Dynamic: summary
